azure_costs_exporter/__init__.py
azure_costs_exporter/allocated_vm_collector.py
azure_costs_exporter/enterprise_billing_collector.py
azure_costs_exporter/main.py
azure_costs_exporter/reserved_vm_collector.py
azure_costs_exporter/views.py
azure_costs_exporter-1.1.0.post1.dist-info/METADATA
azure_costs_exporter-1.1.0.post1.dist-info/RECORD
azure_costs_exporter-1.1.0.post1.dist-info/WHEEL
azure_costs_exporter-1.1.0.post1.dist-info/top_level.txt
