Metadata-Version: 2.1
Name: azure-costs-exporter
Version: 1.1.0.post1
Summary: A Prometheus exporter for the Azure billing API
Home-page: https://github.com/blue-yonder/azure-cost-mon
Author: Manuel Bähr
Author-email: manuel.baehr@blue-yonder.com
License: UNKNOWN
Platform: UNKNOWN
Classifier: Development Status :: 4 - Beta
Classifier: Intended Audience :: Developers
Classifier: Intended Audience :: System Administrators
Classifier: License :: OSI Approved :: MIT License
Classifier: Operating System :: POSIX :: Linux
Classifier: Operating System :: MacOS :: MacOS X
Classifier: Programming Language :: Python
Classifier: Topic :: System :: Monitoring
Requires-Dist: flask
Requires-Dist: requests
Requires-Dist: numpy
Requires-Dist: pandas
Requires-Dist: prometheus-client
Requires-Dist: azure-mgmt-compute
Requires-Dist: azure-mgmt-reservations
